{"resources/sounds/coint.mp3":{},"resources/sounds/gameover.mp3":{},"resources/sounds/jump.mp3":{},"resources/sounds/overworld.mp3":{},"resources/images/overworld_bg.png":{"w":600,"marginBottom":0,"scale":1,"marginLeft":0,"marginTop":0,"marginRight":0,"group":"resources-images","sheet":"spritesheets/resources-images0.png","h":385,"y":2,"sheetSize":[1024,512],"x":2},"resources/images/enemies/turtle1.png":{"w":32,"marginBottom":0,"scale":1,"marginLeft":0,"marginTop":0,"marginRight":0,"group":"resources-images-enemies","sheet":"spritesheets/resources-images-enemies0.png","h":54,"y":2,"sheetSize":[256,128],"x":74},"resources/images/mario/mario_super_jump-1.png":{"w":32,"marginBottom":0,"scale":1,"marginLeft":3,"marginTop":2,"marginRight":3,"group":"resources-images-mario","sheet":"spritesheets/resources-images-mario0.png","h":52,"y":2,"sheetSize":[512,64],"x":80},"resources/images/mario/mario_run-1.png":{"w":30,"marginBottom":0,"scale":1,"marginLeft":1,"marginTop":0,"marginRight":1,"group":"resources-images-mario","sheet":"spritesheets/resources-images-mario0.png","h":32,"y":2,"sheetSize":[512,64],"x":292},"resources/images/mario/mario_super_run-4.png":{"w":28,"marginBottom":0,"scale":1,"marginLeft":5,"marginTop":0,"marginRight":5,"group":"resources-images-mario","sheet":"spritesheets/resources-images-mario0.png","h":54,"y":2,"sheetSize":[512,64],"x":152},"resources/mario33.png":{"w":870,"marginBottom":0,"scale":1,"marginLeft":0,"marginTop":0,"marginRight":0,"group":"resources-","sheet":"spritesheets/resources-0.png","h":1139,"y":0,"sheetSize":[870,1139],"x":0},"resources/images/coint.png":{"w":28,"marginBottom":0,"scale":1,"marginLeft":0,"marginTop":0,"marginRight":0,"group":"resources-images","sheet":"spritesheets/resources-images0.png","h":32,"y":2,"sheetSize":[1024,512],"x":606},"resources/images/enemies/turtle2.png":{"w":32,"marginBottom":0,"scale":1,"marginLeft":0,"marginTop":2,"marginRight":0,"group":"resources-images-enemies","sheet":"spritesheets/resources-images-enemies0.png","h":52,"y":2,"sheetSize":[256,128],"x":110},"resources/images/mario/mario_fly-1.png":{"w":32,"marginBottom":0,"scale":1,"marginLeft":0,"marginTop":0,"marginRight":0,"group":"resources-images-mario","sheet":"spritesheets/resources-images-mario0.png","h":32,"y":2,"sheetSize":[512,64],"x":184},"resources/images/mario/mario_jump-1.png":{"w":32,"marginBottom":0,"scale":1,"marginLeft":0,"marginTop":0,"marginRight":0,"group":"resources-images-mario","sheet":"spritesheets/resources-images-mario0.png","h":32,"y":2,"sheetSize":[512,64],"x":220},"resources/images/mario/mario_run-3.png":{"w":32,"marginBottom":0,"scale":1,"marginLeft":0,"marginTop":0,"marginRight":0,"group":"resources-images-mario","sheet":"spritesheets/resources-images-mario0.png","h":32,"y":2,"sheetSize":[512,64],"x":256},"resources/images/mario/mario_run-2.png":{"w":24,"marginBottom":0,"scale":1,"marginLeft":4,"marginTop":3,"marginRight":4,"group":"resources-images-mario","sheet":"spritesheets/resources-images-mario0.png","h":30,"y":2,"sheetSize":[512,64],"x":326},"resources/images/mario/mario_run-4.png":{"w":24,"marginBottom":0,"scale":1,"marginLeft":4,"marginTop":3,"marginRight":4,"group":"resources-images-mario","sheet":"spritesheets/resources-images-mario0.png","h":30,"y":2,"sheetSize":[512,64],"x":326},"resources/images/enemies/flower2.png":{"w":32,"marginBottom":0,"scale":1,"marginLeft":0,"marginTop":2,"marginRight":0,"group":"resources-images-enemies","sheet":"spritesheets/resources-images-enemies0.png","h":64,"y":2,"sheetSize":[256,128],"x":38},"resources/images/mario/mario_super_fly-1.png":{"w":38,"marginBottom":0,"scale":1,"marginLeft":0,"marginTop":2,"marginRight":0,"group":"resources-images-mario","sheet":"spritesheets/resources-images-mario0.png","h":52,"y":2,"sheetSize":[512,64],"x":2},"resources/images/enemies/flower1.png":{"w":32,"marginBottom":0,"scale":1,"marginLeft":0,"marginTop":0,"marginRight":0,"group":"resources-images-enemies","sheet":"spritesheets/resources-images-enemies0.png","h":66,"y":2,"sheetSize":[256,128],"x":2},"resources/images/mario/mario_super_run-2.png":{"w":28,"marginBottom":0,"scale":1,"marginLeft":5,"marginTop":0,"marginRight":5,"group":"resources-images-mario","sheet":"spritesheets/resources-images-mario0.png","h":54,"y":2,"sheetSize":[512,64],"x":152},"resources/images/mario/mario_super_run-1.png":{"w":32,"marginBottom":0,"scale":1,"marginLeft":3,"marginTop":0,"marginRight":3,"group":"resources-images-mario","sheet":"spritesheets/resources-images-mario0.png","h":54,"y":2,"sheetSize":[512,64],"x":44},"resources/images/mario/mario_super_run-3.png":{"w":32,"marginBottom":0,"scale":1,"marginLeft":3,"marginTop":2,"marginRight":3,"group":"resources-images-mario","sheet":"spritesheets/resources-images-mario0.png","h":52,"y":2,"sheetSize":[512,64],"x":116}}